new_python_github_project/__init__.py
new_python_github_project/main.py
new_python_github_project-0.1.0.dist-info/LICENSE
new_python_github_project-0.1.0.dist-info/METADATA
new_python_github_project-0.1.0.dist-info/WHEEL
new_python_github_project-0.1.0.dist-info/entry_points.txt
new_python_github_project-0.1.0.dist-info/RECORD
